WebPyCookbookZhongwenban/README.md
WebPyCookbookZhongwenban/__init__.py
WebPyCookbookZhongwenban/__main__.py
WebPyCookbookZhongwenban/file.epub
WebPyCookbookZhongwenban/index.html
WebPyCookbookZhongwenban/css/__init__.py
WebPyCookbookZhongwenban/css/annotations.css
WebPyCookbookZhongwenban/css/main.css
WebPyCookbookZhongwenban/css/normalize.css
WebPyCookbookZhongwenban/css/popup.css
WebPyCookbookZhongwenban/font/__init__.py
WebPyCookbookZhongwenban/font/fontello.eot
WebPyCookbookZhongwenban/font/fontello.svg
WebPyCookbookZhongwenban/font/fontello.ttf
WebPyCookbookZhongwenban/font/fontello.woff
WebPyCookbookZhongwenban/img/__init__.py
WebPyCookbookZhongwenban/img/annotator-glyph-sprite.png
WebPyCookbookZhongwenban/img/annotator-icon-sprite.png
WebPyCookbookZhongwenban/img/apple-touch-icon.png
WebPyCookbookZhongwenban/img/cancelfullscreen.png
WebPyCookbookZhongwenban/img/close.png
WebPyCookbookZhongwenban/img/fullscreen.png
WebPyCookbookZhongwenban/img/loader.gif
WebPyCookbookZhongwenban/img/menu-icon.png
WebPyCookbookZhongwenban/img/save.png
WebPyCookbookZhongwenban/img/saved.png
WebPyCookbookZhongwenban/img/settings-s.png
WebPyCookbookZhongwenban/img/settings.png
WebPyCookbookZhongwenban/img/star.png
WebPyCookbookZhongwenban/js/__init__.py
WebPyCookbookZhongwenban/js/epub.js
WebPyCookbookZhongwenban/js/epub.min.js
WebPyCookbookZhongwenban/js/epub.min.map
WebPyCookbookZhongwenban/js/hooks.min.js
WebPyCookbookZhongwenban/js/hooks.min.map
WebPyCookbookZhongwenban/js/reader.js
WebPyCookbookZhongwenban/js/reader.js.map
WebPyCookbookZhongwenban/js/reader.min.js
WebPyCookbookZhongwenban/js/reader.min.map
WebPyCookbookZhongwenban/js/hooks/__init__.py
WebPyCookbookZhongwenban/js/hooks/extensions/__init__.py
WebPyCookbookZhongwenban/js/hooks/extensions/highlight.js
WebPyCookbookZhongwenban/js/libs/__init__.py
WebPyCookbookZhongwenban/js/libs/jquery.min.js
WebPyCookbookZhongwenban/js/libs/localforage.min.js
WebPyCookbookZhongwenban/js/libs/screenfull.js
web_py_cookbook_zhongwenban-2024.3.2.0.dist-info/METADATA
web_py_cookbook_zhongwenban-2024.3.2.0.dist-info/WHEEL
web_py_cookbook_zhongwenban-2024.3.2.0.dist-info/entry_points.txt
web_py_cookbook_zhongwenban-2024.3.2.0.dist-info/top_level.txt
web_py_cookbook_zhongwenban-2024.3.2.0.dist-info/RECORD
